pydantic_pystac_extensions/__init__.py
pydantic_pystac_extensions/core.py
pydantic_pystac_extensions/py.typed
pydantic_pystac_extensions/schema.py
pydantic_pystac_extensions/testing.py
pydantic_pystac_extensions-0.3.4.dist-info/licenses/LICENSE
pydantic_pystac_extensions-0.3.4.dist-info/METADATA
pydantic_pystac_extensions-0.3.4.dist-info/WHEEL
pydantic_pystac_extensions-0.3.4.dist-info/top_level.txt
pydantic_pystac_extensions-0.3.4.dist-info/RECORD
